mooney_maker/__init__.py
mooney_maker/core.py
mooney_maker/DiffusionEdge/LICENSE
mooney_maker/DiffusionEdge/__init__.py
mooney_maker/DiffusionEdge/diffedge.py
mooney_maker/DiffusionEdge/denoising_diffusion_pytorch/__init__.py
mooney_maker/DiffusionEdge/denoising_diffusion_pytorch/data.py
mooney_maker/DiffusionEdge/denoising_diffusion_pytorch/ddm_const_sde.py
mooney_maker/DiffusionEdge/denoising_diffusion_pytorch/encoder_decoder.py
mooney_maker/DiffusionEdge/denoising_diffusion_pytorch/loss.py
mooney_maker/DiffusionEdge/denoising_diffusion_pytorch/mask_cond_unet.py
mooney_maker/DiffusionEdge/denoising_diffusion_pytorch/swin_transformer.py
mooney_maker/DiffusionEdge/denoising_diffusion_pytorch/utils.py
mooney_maker/DiffusionEdge/taming/__init__.py
mooney_maker/DiffusionEdge/taming/util.py
mooney_maker/DiffusionEdge/taming/modules/util.py
mooney_maker/DiffusionEdge/taming/modules/discriminator/model.py
mooney_maker/DiffusionEdge/taming/modules/losses/__init__.py
mooney_maker/DiffusionEdge/taming/modules/losses/lpips.py
mooney_maker/DiffusionEdge/taming/modules/losses/segmentation.py
mooney_maker/DiffusionEdge/taming/modules/losses/util.py
mooney_maker/DiffusionEdge/taming/modules/losses/vqperceptual.py
mooney_maker/TEED/LICENSE
mooney_maker/TEED/loss2.py
mooney_maker/TEED/ted.py
mooney_maker/TEED/checkpoints/TEED.pth
mooney_maker/TEED/utils/AF/Fsmish.py
mooney_maker/TEED/utils/AF/Xsmish.py
mooney_maker/techniques/__init__.py
mooney_maker/techniques/base.py
mooney_maker/techniques/basic_global.py
mooney_maker/techniques/edge_optimization_techniques/__init__.py
mooney_maker/techniques/edge_optimization_techniques/edge_optimization_techniques.py
mooney_maker/techniques/edge_optimization_techniques/eval_teed.py
mooney_maker/techniques/edge_optimization_techniques/optimizers.py
mooney_maker/utils/__init__.py
mooney_maker/utils/io.py
mooney_maker/utils/load_models.py
mooney_maker/utils/visualization.py
mooney_maker-0.1.1.dist-info/licenses/LICENSE
mooney_maker-0.1.1.dist-info/licenses/src/mooney_maker/DiffusionEdge/LICENSE
mooney_maker-0.1.1.dist-info/licenses/src/mooney_maker/TEED/LICENSE
mooney_maker-0.1.1.dist-info/METADATA
mooney_maker-0.1.1.dist-info/WHEEL
mooney_maker-0.1.1.dist-info/top_level.txt
mooney_maker-0.1.1.dist-info/RECORD
