Metadata-Version: 2.4
Name: mooney-maker
Version: 0.1.1
Summary: A Python package to automatically create ambiguous Mooney (two-tone) images
Author-email: Lars Reining <lars.reining@stud.tu-darmstadt.de>
License-Expression: MIT
Project-URL: Homepage, https://github.com/ag-perception-wallis-lab/mooney_maker
Project-URL: Issues, https://github.com/ag-perception-wallis-lab/mooney_maker/issues
Requires-Python: >=3.11
License-File: LICENSE
License-File: src/mooney_maker/DiffusionEdge/LICENSE
License-File: src/mooney_maker/TEED/LICENSE
Requires-Dist: einops>=0.8.1
Requires-Dist: fvcore>=0.1.5.post20221221
Requires-Dist: huggingface-hub>=0.33.2
Requires-Dist: matplotlib>=3.10.1
Requires-Dist: opencv-python>=4.11.0.86
Requires-Dist: requests>=2.32.4
Requires-Dist: scikit-image>=0.25.2
Requires-Dist: torch>=2.6.0
Requires-Dist: torchvision>=0.21.0
Dynamic: license-file
